web_fishing/__init__.py
web_fishing/__main__.py
web_fishing/py.typed
web_fishing-0.0.1.dist-info/LICENSE
web_fishing-0.0.1.dist-info/METADATA
web_fishing-0.0.1.dist-info/WHEEL
web_fishing-0.0.1.dist-info/entry_points.txt
web_fishing-0.0.1.dist-info/RECORD
