Metadata-Version: 2.1
Name: web-fishing
Version: 0.0.1
Summary: Web Fishing
Home-page: https://github.com/56kyle/web-fishing
License: MIT
Author: Kyle Oliver
Author-email: 56kyleoliver@gmail.com
Requires-Python: >=3.9,<4.0
Classifier: Development Status :: 1 - Planning
Classifier: License :: OSI Approved :: MIT License
Classifier: Programming Language :: Python :: 3
Classifier: Programming Language :: Python :: 3.9
Classifier: Programming Language :: Python :: 3.10
Classifier: Programming Language :: Python :: 3.11
Requires-Dist: click (>=8.0.1)
Requires-Dist: loguru (>=0.7.2,<0.8.0)
Requires-Dist: platformdirs (>=4.2.2,<5.0.0)
Project-URL: Changelog, https://github.com/56kyle/web-fishing/releases
Project-URL: Documentation, https://web-fishing.readthedocs.io
Project-URL: Repository, https://github.com/56kyle/web-fishing
